pis/__init__.py
pis/pypis.py
pypis-0.1.1.dist-info/LICENSE
pypis-0.1.1.dist-info/METADATA
pypis-0.1.1.dist-info/WHEEL
pypis-0.1.1.dist-info/entry_points.txt
pypis-0.1.1.dist-info/top_level.txt
pypis-0.1.1.dist-info/RECORD
