Metadata-Version: 2.1
Name: pypis
Version: 0.1.1
Summary: search and find package
Author-email: z2y <jiyvn.liu@aliyun.com>
Project-URL: Homepage, https://github.com/Jiyvn/pypis
Project-URL: Bug Tracker, https://github.com/Jiyvn/pypis/issues
Classifier: Environment :: Console
Classifier: Environment :: Console :: Curses
Classifier: Programming Language :: Python :: 3
Classifier: License :: OSI Approved :: Apache Software License
Classifier: Operating System :: OS Independent
Requires-Python: >=3.0
License-File: LICENSE
Requires-Dist: requests
